CHANGELOG.md
README.md
busker/__init__.py
busker/actions.py
busker/executive.py
busker/gui.py
busker/history.py
busker/main.py
busker/proofer.py
busker/runner.py
busker/scraper.py
busker/stager.py
busker/tagger.py
busker/types.py
busker/visitor.py
busker/zone.py
busker/test/.test_stager.py.swp
busker/test/__init__.py
busker/test/test_executive.py
busker/test/test_history.py
busker/test/test_proofer.py
busker/test/test_runner.py
busker/test/test_scenario_01.stage.toml
busker/test/test_scenario_02.stage.toml
busker/test/test_scenario_03.stage.toml
busker/test/test_scraper.py
busker/test/test_stager.py
busker/test/test_tagger.py
busker/test/test_zone.py
busker/utils/__init__.py
busker/utils/fruition.svg
busker/utils/graph.py
busker/utils/proofread.py
busker/utils/rotu-puzzle.stage.toml
busker-0.22.0.dist-info/METADATA
busker-0.22.0.dist-info/WHEEL
busker-0.22.0.dist-info/entry_points.txt
busker-0.22.0.dist-info/licenses/LICENSE
busker-0.22.0.dist-info/RECORD
