Metadata-Version: 2.4
Name: busker
Version: 0.22.0
Summary: A utility for testing Balladeer projects.
Author-email: D E Haynes <tundish@gigeconomy.org.uk>
Maintainer-email: Tundish <tundish@gigeconomy.org.uk>
License:                     GNU GENERAL PUBLIC LICENSE
License-File: LICENSE
Keywords: balladeer,interactive fiction
Classifier: Development Status :: 4 - Beta
Classifier: Programming Language :: Python
Requires-Python: >=3.11
Provides-Extra: test
